dicom_client/__init__.py
dicom_client/client.py
dicom_client/metadata_utils.py
dicom_client/token.py
tests/__init__.py
tests/conftest.py
tests/integration/__init__.py
tests/integration/test_dicom_client.py
tests/unit/__init__.py
tests/unit/test_dicomclient.py
dicom_client_python-0.3.1.dist-info/LICENSE.txt
dicom_client_python-0.3.1.dist-info/METADATA
dicom_client_python-0.3.1.dist-info/WHEEL
dicom_client_python-0.3.1.dist-info/top_level.txt
dicom_client_python-0.3.1.dist-info/RECORD
