Metadata-Version: 2.1
Name: dicom-client-python
Version: 0.3.1
Summary: A small dicom client in python
Home-page: https://github.com/microsoft/dicom-client-python
Author: Braveheart
Author-email: bterkaly@microsoft.com
License: UNKNOWN
Platform: UNKNOWN
Classifier: Programming Language :: Python :: 3
Classifier: License :: OSI Approved :: MIT License
Classifier: Operating System :: OS Independent
Requires-Python: >=3.7
Requires-Dist: pydicom (==2.1.1)
Requires-Dist: requests-toolbelt (==0.9.1)
Requires-Dist: pyodbc (==4.0.30)
Requires-Dist: urllib3 (==1.26.2)
Requires-Dist: requests (==2.25.0)
Requires-Dist: adal (==1.2.5)
Requires-Dist: PyJWT (==1.7.1)
